django_cfg/README.md
django_cfg/__init__.py
django_cfg/apps.py
django_cfg/config.py
django_cfg/requirements.txt
django_cfg/apps/__init__.py
django_cfg/apps/urls.py
django_cfg/apps/api/__init__.py
django_cfg/apps/api/commands/__init__.py
django_cfg/apps/api/commands/serializers.py
django_cfg/apps/api/commands/urls.py
django_cfg/apps/api/commands/views.py
django_cfg/apps/api/dashboard/TRANSACTION_FIX.md
django_cfg/apps/api/dashboard/__init__.py
django_cfg/apps/api/dashboard/apps.py
django_cfg/apps/api/dashboard/urls.py
django_cfg/apps/api/dashboard/serializers/__init__.py
django_cfg/apps/api/dashboard/serializers/activity.py
django_cfg/apps/api/dashboard/serializers/apizones.py
django_cfg/apps/api/dashboard/serializers/base.py
django_cfg/apps/api/dashboard/serializers/charts.py
django_cfg/apps/api/dashboard/serializers/commands.py
django_cfg/apps/api/dashboard/serializers/config.py
django_cfg/apps/api/dashboard/serializers/metrics.py
django_cfg/apps/api/dashboard/serializers/overview.py
django_cfg/apps/api/dashboard/serializers/statistics.py
django_cfg/apps/api/dashboard/serializers/system.py
django_cfg/apps/api/dashboard/services/__init__.py
django_cfg/apps/api/dashboard/services/apizones_service.py
django_cfg/apps/api/dashboard/services/charts_service.py
django_cfg/apps/api/dashboard/services/commands_security.py
django_cfg/apps/api/dashboard/services/commands_service.py
django_cfg/apps/api/dashboard/services/config_service.py
django_cfg/apps/api/dashboard/services/metrics_service.py
django_cfg/apps/api/dashboard/services/overview_service.py
django_cfg/apps/api/dashboard/services/statistics_service.py
django_cfg/apps/api/dashboard/services/system_health_service.py
django_cfg/apps/api/dashboard/views/__init__.py
django_cfg/apps/api/dashboard/views/activity_views.py
django_cfg/apps/api/dashboard/views/apizones_views.py
django_cfg/apps/api/dashboard/views/charts_views.py
django_cfg/apps/api/dashboard/views/commands_views.py
django_cfg-1.5.213.dist-info/METADATA
django_cfg-1.5.213.dist-info/WHEEL
django_cfg-1.5.213.dist-info/entry_points.txt
django_cfg-1.5.213.dist-info/licenses/LICENSE
django_cfg-1.5.213.dist-info/RECORD
