Metadata-Version: 2.4
Name: django-cfg
Version: 1.5.213
Summary: Modern Django framework with type-safe Pydantic v2 configuration, Next.js admin integration, real-time WebSockets, and 8 enterprise apps. Replace settings.py with validated models,  90% less code. Production-ready with AI agents, auto-generated TypeScript clients,  and zero-config features.
Project-URL: Homepage, https://djangocfg.com
Project-URL: Documentation, https://djangocfg.com
Project-URL: Repository, https://github.com/markolofsen/django-cfg
Project-URL: Issues, https://github.com/markolofsen/django-cfg/issues
Project-URL: Changelog, https://github.com/markolofsen/django-cfg/blob/main/CHANGELOG.md
Author-email: Django-CFG Team <info@djangocfg.com>
Maintainer-email: Django-CFG Team <info@djangocfg.com>
License: MIT
License-File: LICENSE
Keywords: ai-agents,centrifugo,configuration,django,django-environ,django-settings,enterprise-django,ide-autocomplete,modern-django,nextjs-admin,pydantic,pydantic-settings,react-admin,real-time,settings,startup-validation,type-safe-config,type-safety,typescript-generation,websocket
Classifier: Development Status :: 4 - Beta
Classifier: Framework :: Django
Classifier: Framework :: Django :: 5.2
Classifier: Intended Audience :: Developers
Classifier: License :: OSI Approved :: MIT License
Classifier: Operating System :: OS Independent
Classifier: Programming Language :: Python
Classifier: Programming Language :: Python :: 3
Classifier: Programming Language :: Python :: 3.12
Classifier: Programming Language :: Python :: 3.13
Classifier: Topic :: Internet :: WWW/HTTP
Classifier: Topic :: Internet :: WWW/HTTP :: Dynamic Content
Classifier: Topic :: Software Development :: Libraries :: Python Modules
Classifier: Topic :: System :: Systems Administration
Classifier: Typing :: Typed
Requires-Python: <3.14,>=3.12
Requires-Dist: adrf<0.2.0,>=0.1.11
Requires-Dist: beautifulsoup4<5.0,>=4.13.0
Requires-Dist: cachetools<7.0,>=5.3.0
Requires-Dist: click<9.0,>=8.2.0
Requires-Dist: cloudflare<5.0,>=4.3.0
Requires-Dist: colorlog<7.0,>=6.9.0
Requires-Dist: coolname<3.0,>=2.2.0
Requires-Dist: cryptography>=44.0.0
Requires-Dist: dj-database-url<4.0,>=3.0.0
Requires-Dist: django-admin-rangefilter<1.0,>=0.13.0
Requires-Dist: django-axes[ipware]<9.0.0,>=8.0.0
Requires-Dist: django-constance<5.0,>=4.3.0
Requires-Dist: django-cors-headers<5.0,>=4.7.0
Requires-Dist: django-extensions<5.0,>=4.1.0
Requires-Dist: django-filter<26.0,>=25.0
Requires-Dist: django-import-export<5.0,>=4.3.0
Requires-Dist: django-json-widget<3.0,>=2.0.0
Requires-Dist: django-ratelimit<5.0.0,>=4.1.0
Requires-Dist: django-redis<7.0,>=6.0.0
Requires-Dist: django-tailwind[reload]<5.0.0,>=4.2.0
Requires-Dist: django-unfold>=0.73.1
Requires-Dist: djangorestframework-simplejwt<6.0,>=5.5.0
Requires-Dist: djangorestframework-simplejwt[token-blacklist]<6.0,>=5.5.0
Requires-Dist: djangorestframework<4.0,>=3.16.0
Requires-Dist: drf-nested-routers<1.0,>=0.94.0
Requires-Dist: drf-spectacular-sidecar<2026.0,>=2025.8.0
Requires-Dist: drf-spectacular<1.0,>=0.28.0
Requires-Dist: geopy<3.0,>=2.4.0
Requires-Dist: hiredis<4.0,>=2.0.0
Requires-Dist: httpx<1.0,>=0.28.1
Requires-Dist: jinja2<4.0.0,>=3.1.6
Requires-Dist: loguru<1.0,>=0.7.0
Requires-Dist: lxml<7.0,>=6.0.0
Requires-Dist: mistune<4.0,>=3.1.4
Requires-Dist: mypy<2.0.0,>=1.18.2
Requires-Dist: ngrok>=1.5.1; python_version >= '3.12'
Requires-Dist: openai<3.0,>=1.107.0
Requires-Dist: pgvector<1.0,>=0.4.0
Requires-Dist: psutil>=7.0.0
Requires-Dist: psycopg[binary,pool]<4.0,>=3.2.0
Requires-Dist: pydantic-settings<3.0.0,>=2.11.0
Requires-Dist: pydantic<3.0,>=2.11.0
Requires-Dist: pydantic[email]<3.0,>=2.11.0
Requires-Dist: pygments<3.0,>=2.19.0
Requires-Dist: pyotp<3.0,>=2.9.0
Requires-Dist: pytelegrambotapi<5.0,>=4.28.0
Requires-Dist: python-json-logger<4.0,>=3.3.0
Requires-Dist: pywebpush<3.0,>=2.0.0
Requires-Dist: pyyaml<7.0,>=6.0
Requires-Dist: qrcode<9.0,>=8.2
Requires-Dist: questionary<3.0,>=2.1.0
Requires-Dist: redis<7.0,>=6.4.0
Requires-Dist: requests<3.0,>=2.32.0
Requires-Dist: rich<15.0,>=14.0.0
Requires-Dist: setuptools>=75.0.0; python_version >= '3.13'
Requires-Dist: tenacity<10.0.0,>=9.1.2
Requires-Dist: tiktoken<1.0,>=0.11.0
Requires-Dist: toml<0.11.0,>=0.10.2
Requires-Dist: toon-python<1.0,>=0.1.2
Requires-Dist: tzlocal<6.0,>=5.3.1
Requires-Dist: whitenoise<7.0,>=6.8.0
Provides-Extra: ai
Requires-Dist: pydantic-ai<2.0,>=1.34.0; extra == 'ai'
Provides-Extra: centrifugo
Requires-Dist: cent<6.0,>=5.0.0; extra == 'centrifugo'
Requires-Dist: websockets<15.0,>=13.0; extra == 'centrifugo'
Provides-Extra: dev
Requires-Dist: betterproto2-compiler<1.0,>=0.9.0; extra == 'dev'
Requires-Dist: black>=23.0; extra == 'dev'
Requires-Dist: build>=1.0; extra == 'dev'
Requires-Dist: django<6.0,>=5.2; extra == 'dev'
Requires-Dist: factory-boy>=3.0; extra == 'dev'
Requires-Dist: fakeredis>=2.0; extra == 'dev'
Requires-Dist: flake8>=5.0; extra == 'dev'
Requires-Dist: isort>=5.0; extra == 'dev'
Requires-Dist: mkdocs-material>=9.0; extra == 'dev'
Requires-Dist: mkdocs>=1.5; extra == 'dev'
Requires-Dist: mkdocstrings[python]>=0.24; extra == 'dev'
Requires-Dist: mypy>=1.0; extra == 'dev'
Requires-Dist: pre-commit>=3.0; extra == 'dev'
Requires-Dist: pytest-cov>=4.0; extra == 'dev'
Requires-Dist: pytest-django>=4.5; extra == 'dev'
Requires-Dist: pytest-mock>=3.0; extra == 'dev'
Requires-Dist: pytest>=7.0; extra == 'dev'
Requires-Dist: questionary>=2.0; extra == 'dev'
Requires-Dist: redis>=5.0; extra == 'dev'
Requires-Dist: rich>=13.0; extra == 'dev'
Requires-Dist: tomlkit>=0.11; extra == 'dev'
Requires-Dist: twine>=4.0; extra == 'dev'
Provides-Extra: django52
Requires-Dist: django<6.0,>=5.2; extra == 'django52'
Provides-Extra: docs
Requires-Dist: mkdocs-material>=9.0; extra == 'docs'
Requires-Dist: mkdocs>=1.5; extra == 'docs'
Requires-Dist: mkdocstrings[python]>=0.24; extra == 'docs'
Requires-Dist: pymdown-extensions>=10.0; extra == 'docs'
Provides-Extra: full
Requires-Dist: aiobreaker<2.0,>=1.2.0; extra == 'full'
Requires-Dist: betterproto2[all]<1.0,>=0.9.0; extra == 'full'
Requires-Dist: black>=23.0; extra == 'full'
Requires-Dist: build>=1.0; extra == 'full'
Requires-Dist: cent<6.0,>=5.0.0; extra == 'full'
Requires-Dist: django-rq>=3.0; extra == 'full'
Requires-Dist: django<6.0,>=5.2; extra == 'full'
Requires-Dist: factory-boy>=3.0; extra == 'full'
Requires-Dist: flake8>=5.0; extra == 'full'
Requires-Dist: grpcio-health-checking<2.0,>=1.50.0; extra == 'full'
Requires-Dist: grpcio-reflection<2.0,>=1.50.0; extra == 'full'
Requires-Dist: grpcio-tools<2.0,>=1.50.0; extra == 'full'
Requires-Dist: grpcio<2.0,>=1.50.0; extra == 'full'
Requires-Dist: grpclib<1.0,>=0.4.8; extra == 'full'
Requires-Dist: hiredis>=2.0; extra == 'full'
Requires-Dist: isort>=5.0; extra == 'full'
Requires-Dist: mkdocs-material>=9.0; extra == 'full'
Requires-Dist: mkdocs>=1.5; extra == 'full'
Requires-Dist: mkdocstrings[python]>=0.24; extra == 'full'
Requires-Dist: mypy>=1.0; extra == 'full'
Requires-Dist: pre-commit>=3.0; extra == 'full'
Requires-Dist: protobuf<7.0,>=5.0; extra == 'full'
Requires-Dist: pydantic-ai<2.0,>=1.34.0; extra == 'full'
Requires-Dist: pymdown-extensions>=10.0; extra == 'full'
Requires-Dist: pytest-cov>=4.0; extra == 'full'
Requires-Dist: pytest-django>=4.5; extra == 'full'
Requires-Dist: pytest-mock>=3.0; extra == 'full'
Requires-Dist: pytest-xdist>=3.0; extra == 'full'
Requires-Dist: pytest>=7.0; extra == 'full'
Requires-Dist: questionary>=2.0; extra == 'full'
Requires-Dist: redis>=5.0; extra == 'full'
Requires-Dist: rich>=13.0; extra == 'full'
Requires-Dist: rq-scheduler>=0.13; extra == 'full'
Requires-Dist: rq>=1.0; extra == 'full'
Requires-Dist: stamina<26.0,>=25.2.0; extra == 'full'
Requires-Dist: structlog<26.0,>=24.0.0; extra == 'full'
Requires-Dist: tomlkit>=0.11; extra == 'full'
Requires-Dist: twine>=4.0; extra == 'full'
Requires-Dist: websockets<15.0,>=13.0; extra == 'full'
Provides-Extra: geo
Provides-Extra: grpc
Requires-Dist: aiobreaker<2.0,>=1.2.0; extra == 'grpc'
Requires-Dist: betterproto2[all]<1.0,>=0.9.0; extra == 'grpc'
Requires-Dist: grpcio-health-checking<2.0,>=1.50.0; extra == 'grpc'
Requires-Dist: grpcio-reflection<2.0,>=1.50.0; extra == 'grpc'
Requires-Dist: grpcio-tools<2.0,>=1.50.0; extra == 'grpc'
Requires-Dist: grpcio<2.0,>=1.50.0; extra == 'grpc'
Requires-Dist: grpclib<1.0,>=0.4.8; extra == 'grpc'
Requires-Dist: protobuf<7.0,>=5.0; extra == 'grpc'
Requires-Dist: stamina<26.0,>=25.2.0; extra == 'grpc'
Requires-Dist: structlog<26.0,>=24.0.0; extra == 'grpc'
Provides-Extra: local
Provides-Extra: rq
Requires-Dist: django-rq>=3.0; extra == 'rq'
Requires-Dist: hiredis>=2.0; extra == 'rq'
Requires-Dist: redis>=5.0; extra == 'rq'
Requires-Dist: rq-scheduler>=0.13; extra == 'rq'
Requires-Dist: rq>=1.0; extra == 'rq'
Provides-Extra: tasks
Requires-Dist: redis>=5.0; extra == 'tasks'
Provides-Extra: test
Requires-Dist: django<6.0,>=5.2; extra == 'test'
Requires-Dist: factory-boy>=3.0; extra == 'test'
Requires-Dist: fakeredis>=2.0; extra == 'test'
Requires-Dist: pytest-cov>=4.0; extra == 'test'
Requires-Dist: pytest-django>=4.5; extra == 'test'
Requires-Dist: pytest-mock>=3.0; extra == 'test'
Requires-Dist: pytest-xdist>=3.0; extra == 'test'
Requires-Dist: pytest>=7.0; extra == 'test'
